smiles_autoencoder/__init__.py
smiles_autoencoder/encoding.py
smiles_autoencoder/model.py
smiles_autoencoder-0.1.0.dist-info/LICENSE
smiles_autoencoder-0.1.0.dist-info/METADATA
smiles_autoencoder-0.1.0.dist-info/WHEEL
smiles_autoencoder-0.1.0.dist-info/top_level.txt
smiles_autoencoder-0.1.0.dist-info/RECORD
