Metadata-Version: 2.1
Name: smiles_autoencoder
Version: 0.1.0
Summary: Autoencoders for SMILES strings
Author-email: Travis Kessler <travis.j.kessler@gmail.com>
Project-URL: Homepage, https://github.com/tjkessler/smiles-autoencoder
Project-URL: Bug Tracker, https://github.com/tjkessler/smiles-autoencoder/issues
Classifier: Programming Language :: Python :: 3.11
Classifier: License :: OSI Approved :: GNU General Public License v3 (GPLv3)
Classifier: Operating System :: OS Independent
Requires-Python: >=3.11
License-File: LICENSE
Requires-Dist: numpy ==2.0.0
Requires-Dist: scikit-learn ==1.5.1
Requires-Dist: torch ==2.3.1
